rf_phate/Embeddings.py
rf_phate/RandomForest.py
rf_phate/__init__.py
rf_phate-0.0.3.dist-info/METADATA
rf_phate-0.0.3.dist-info/WHEEL
rf_phate-0.0.3.dist-info/top_level.txt
rf_phate-0.0.3.dist-info/RECORD
