Metadata-Version: 2.1
Name: rf-phate
Version: 0.0.3
Summary: RF-PHATE
Home-page: UNKNOWN
Author: Jake Rhodes
Author-email: jakerhodes@aggiemail.usu.edu
License: GNU General Public License Version 2
Keywords: random forest,proximities,dimensionality reduction
Platform: UNKNOWN
Classifier: Development Status :: 3 - Alpha
Classifier: Intended Audience :: Education
Classifier: Programming Language :: Python :: 3
Classifier: Operating System :: Microsoft :: Windows
